turkic_suffix_library/__init__.py
turkic_suffix_library/azeri.py
turkic_suffix_library/kazakh.py
turkic_suffix_library/turkish.py
turkic_suffix_library/turkmen.py
turkic_suffix_library/uzbek.py
turkic_suffix_library/languages/__init__.py
turkic_suffix_library/languages/azeri/__init__.py
turkic_suffix_library/languages/azeri/azeri_class.py
turkic_suffix_library/languages/common/__init__.py
turkic_suffix_library/languages/common/turkic_class.py
turkic_suffix_library/languages/kazakh/__init__.py
turkic_suffix_library/languages/kazakh/kazakh_class.py
turkic_suffix_library/languages/turkish/__init__.py
turkic_suffix_library/languages/turkish/consonants.py
turkic_suffix_library/languages/turkish/sample_verbs_list.py
turkic_suffix_library/languages/turkish/test_verbs.py
turkic_suffix_library/languages/turkish/turkish_class.py
turkic_suffix_library/languages/turkish/turkish_string.py
turkic_suffix_library/languages/turkmen/__init__.py
turkic_suffix_library/languages/turkmen/constants.py
turkic_suffix_library/languages/turkmen/nouns.py
turkic_suffix_library/languages/turkmen/test.py
turkic_suffix_library/languages/turkmen/turkmen_class.py
turkic_suffix_library/languages/uzbek/__init__.py
turkic_suffix_library/languages/uzbek/uzbek_class.py
turkic_suffix_library-0.1.9.dist-info/licenses/LICENCE
turkic_suffix_library-0.1.9.dist-info/METADATA
turkic_suffix_library-0.1.9.dist-info/WHEEL
turkic_suffix_library-0.1.9.dist-info/top_level.txt
turkic_suffix_library-0.1.9.dist-info/RECORD
