Metadata-Version: 2.4
Name: turkic-suffix-library
Version: 0.1.9
Summary: Turkic suffix library
Home-page: https://github.com/miklagard/turkic-suffix-library
Author: Cem Yildiz, Oguzhan Moroglu, Sadullah Duman
Author-email: cem.yildiz@proton.me
Classifier: Programming Language :: Python :: 3
Classifier: License :: OSI Approved :: MIT License
Classifier: Operating System :: OS Independent
Requires-Python: >=3.6
License-File: LICENCE
Dynamic: author
Dynamic: author-email
Dynamic: classifier
Dynamic: description
Dynamic: description-content-type
Dynamic: home-page
Dynamic: license-file
Dynamic: requires-python
Dynamic: summary
